LICENSE
MANIFEST.in
README.md
requirements.txt
setup.cfg
setup.py
clermontpcr.egg-info/PKG-INFO
clermontpcr.egg-info/SOURCES.txt
clermontpcr.egg-info/dependency_links.txt
clermontpcr.egg-info/entry_points.txt
clermontpcr.egg-info/top_level.txt
cpcr/__init__.py
cpcr/_version.py
cpcr/run.py
tests/__init__.py
tests/context.py
tests/test_clermontpcr.py
webapp/__init__.py
webapp/clermontwebapp.py