Metadata-Version: 1.1
Name: clermontpcr
Version: 0.3.3
Summary: clermontpcr: phylotype your strains, in silico
Home-page: https://github.com/nickp60/clermontpcr
Author: Nick Waters
Author-email: nickp60@gmail.com
License: MIT
Keywords: bioinformatics evolution genomics development
Platform: UNKNOWN
Classifier: Development Status :: 3 - Alpha
Classifier: Intended Audience :: Developers
Classifier: Intended Audience :: Science/Research
Classifier: Topic :: Scientific/Engineering :: Bio-Informatics
Classifier: License :: OSI Approved :: MIT License
Classifier: Programming Language :: Python :: 3.5
Classifier: Programming Language :: Python :: 3.6
